{
    "upload_relative_path": "uploads",
    "download_relative_path": "downloads",
    "ocr_dir_relative_path": "ocrDir",
    "review_backoffice_sheet": true,
    "localhostocrViewURL": "http://localhost/website/tableEdit/ocrViewer.html",
    "localhostboViewURL": "http://localhost/website/tableEdit/boViewer.html",
    "hostAddress": "localhost",
    "forms": [
      {
        "name": "CountryMZ",
        "headers": ["שורה", "פריט", "שם פריט", "כמות", "מחיר מכירה","הנחה","מחיר","מחלקה","הפרשים","מחיר מקורי"],
        "attributesColumns": [{"Price": 7},{"Quantity": 4},{"CatalogNo": 2}, {"Diff":9}, {"OriginalPrice":10},{"SalePrice":5},{"ItemName":3},{"Department":8}],
        "dataTypeColumns": [[2,1],[9,2]],
        "// comment: dataTypeColumns = Type : 1 - string, 2 - percentage ": ["columnIndex","type"],
        "priceListColumns": [{"CatalogNo": 3},{"Price": 9},{"SalePrice": 7}, {"ItemName":2},{"Department":5}],
        "destinationLabelID": "Label_6548702769572887756",
        "emailSourceAddress": "innoventory.tech@soluma.si",
        "landingEmailDirectory": "INBOX",
        "ocrFilesDestinationDirectory": "C:/xampp/htdocs/website/ocrDir",
        "ocrFilesFinalUploadDirectory": "C:/xampp/htdocs/website/uploads",
        "preProcessFilesDirectory": "C:/xampp/htdocs/website/preProcessDir",
        "fetchForBOdirectory": "C:/xampp/htdocs/website/downloads",
        "BOoutputDirectory": "C:/xampp/htdocs/website/toBackOffice",
        "BOtempDirectory": "C:/xampp/htdocs/website/downloads/Temp",
        "preProcessLogfileName": "/filelog.txt",
        "preProcessFROMemailAddress":"inno.ocr@gmail.com",
        "preProcessDestinationEmailAddress":"innoventory.tech@soluma.si",
        "preProcessMethod": "MultiPage",
        "// comment preProcessMethod": "MultiPage, SinglePage",
        "preProcessToSend": 0,
        "// comment preProcessToSend": "0-no email, 1-draft email, 2- send email",
        "customerDestinationEmailAddress": "shimri.lotan@gmail.com",
        "toSendToCustomer": 0,
        "// comment toSendToCustomer": "0-no email, 1-draft email, 2- send email",
        "OCRPicFileExtention": "pdf",
        "// comment OCRfilesExtention": "will fetch the OCR picture file based on the given extention pdf of jpeg",
        "newProductsHeaders": ["מס פריט","שם פריט","ברקוד","מחיר קניה","ספק","מחיר מכירה","מחלקה","שורה מקורית","מזהה חשבונית","שם מחלקה"],
        "toNewProductMapping": [[1,8,1],[2,1,2],[3,2,2],[2,3,2],[7,4,1],[5,6,1],[8,10,1]],
        "// comment: last digit in mapping = Type : 1 - regulat, 2 - string ": "[column at items sheet,column at new product sheet, data type]",
        "newProductsItemsInducators": [10,7,9],
        "// comment newProductsItemsInducators": "[department name column,department number column, invoice identifier column]",
        "processPriceChange": [1,1,3],
        "// comment processPriceChnage [0] - costprice indicator (temp off), [1] - sales price indecator, [2] - threshold in percentage": "",
        "priceChangeHeader": ["שורה", "ברקוד", "מחיר חדש","שם פריט","מחלקה","שינוי עלות","מרווח נוכחי","מרווח מומלץ",
                              "מרווח תיאורטי","מחיר מכירה מקורי","עלות חדשה","מזהה חשבונית","שורה מקורית","שינוי מחיר"],
        "BOpackInvoiceListHeader": ["supplier", "date", "supplierCode", "invoiceNum", "invoiceSum", "remark"],
        "priceChangeMapping": [[2,2,2],[3,4,2],[8,5,1],[9,6,1],[1,13,1],[5,10,1],[7,11,1]],
        "// comment priceChangeMapping [from-column, to-column, data type]": "data types: 1 - regular, 2 - string",
        "priceChangeIndicators": [3,7,1.18,8,9,14,12,10,1.5,2,0.15],
        "// comment priceChangeIndicators": ["[saleNewPriceColumn, originalMarginColumn, VAT_multiplexer,recommendedMarginColumn,",
                                            "possibleMarginColumn,priceChangeIndicatorColumn,invoiceIdintifierColumn,OriginalSalePriceColumn,",
                                            "priceChangeThresholdPercentage,barcodeColumn,maxExtraMargin]"],
        "newProductsForBOheaders": ["מס פריט","שם פריט","ברקוד","מחיר קניה","ספק","מחיר מכירה","מחלקה","שורה מקורית","מזהה חשבונית","שם מחלקה"],
        "supplierColumnAtNewProductsForBOHeaders": 9,
        "BOtype": "comax",
        "// comment BOtype (back office type)": "can be comax or all4shops",
        "departmentsConfigFile":"C:/xampp/htdocs/website/configDir/CountryMZ_Departments.json",
        "BOEmailMessageTxtFile":"C:/xampp/htdocs/website/emailMessages/BO_result_email_message.txt",
        "supervisedProductsFile":"C:/xampp/htdocs/website/configDir/Supervised_products.json",
        "supplierParam": [{"supplierNDepartmentColumns":[5,0]},
                                {"Tnuva": [1210246,1,0]},
                                {"StraussCool":[1210238,1,1]},
                                {"Avikam":[121018,1,0]},
                                {"Ays":[121029,1,0]},
                                {"FarmaDeal":[121024,1,0]},
                                {"Hamefitz":[121025,1,0]},
                                {"Hwine":[121006,1,0]},
                                {"Mashkokit":[121020,1,0]},
                                {"Sbh":[1210201,1,1]},
                                {"Tayari":[121010,1,1]},
                                {"Yehiam":[121034,1,0]},
                                {"Shufersal":[121002,1,0]},
                                {"GoPharm":[121027,1,0]},
                                {"Ewi":[121014,1,0]},
                                {"BNissim":[1210204,1,0]},
                                {"Angel":[1210240,1,0]},
                                {"Etran":[121028,1,0]},
                                {"Oshri":[121031,1,0]},
                                {"Globrands":[121009,1,0]},
                                {"PhilipMorris":[121001,1,0]},
                                {"TnuvaMeat":[1210245,1,0]},
                                {"Mashani":[121032,1,0]},
                                {"GWS":[121033,1,0]},
                                {"Dubek":[121022,1,0]},
                                {"PastaCasa":[121030,1,0]},
                                {"Shamir":[121035,1,0]},
                                {"Akerman":[121008,1,0]},
                                {"Ida":[121036,1,0]},
                                {"Tavili":[121037,1,0]},
                                {"Mayan":[121023,1,1]}],                                
        "// comment 1: supplierParam starcture": {"SupplierName": ["SupplierIndex","DepartmentIndex-not relevant","0-regular, 1-item price = LineTotal/Qty"]},
        "// comment 2: supplierParam ": "in 'supplierNDepartmentColumns':[X,Y] if X or Y = 0, the value will not be in new products sheet",
        "administratorName":"אדיר"
      },
      {
        "name": "RimonMarket",
        "headers": ["שורה", "פריט", "שם פריט", "כמות", "מחיר מכירה","הנחה","מחיר","מחלקה","הפרשים","מחיר מקורי"],
        "attributesColumns": [{"Price": 7},{"Quantity": 4},{"CatalogNo": 2}, {"Diff":9}, {"OriginalPrice":10},{"SalePrice":5},{"ItemName":3},{"Department":8}],
        "dataTypeColumns": [[2,1],[9,2]],
        "// comment: dataTypeColumns = Type : 1 - string, 2 - percentage ": ["columnIndex","type"],
        "priceListColumns": [{"CatalogNo": 1},{"Price": 4},{"SalePrice": 5  }, {"ItemName":3},{"Department":11}],
        "destinationLabelID": "Label_6548702769572887756",
        "emailSourceAddress": "innoventory.tech@soluma.si",
        "landingEmailDirectory": "INBOX",
        "ocrFilesDestinationDirectory": "C:/xampp/htdocs/website/ocrDir",
        "ocrFilesFinalUploadDirectory": "C:/xampp/htdocs/website/uploads",
        "preProcessFilesDirectory": "C:/xampp/htdocs/website/preProcessDir",
        "fetchForBOdirectory": "C:/xampp/htdocs/website/downloads",
        "BOoutputDirectory": "C:/xampp/htdocs/website/toBackOffice",
        "BOtempDirectory": "C:/xampp/htdocs/website/downloads/Temp",
        "preProcessLogfileName": "/filelog.txt",
        "preProcessFROMemailAddress":"inno.ocr@gmail.com",
        "preProcessDestinationEmailAddress":"innoventory.tech@soluma.si",
        "preProcessMethod": "SinglePage",
        "// comment preProcessMethod": "MultiPage, SinglePage",
        "preProcessToSend": 1,
        "// comment preProcessToSend": "0-no email, 1-draft email, 2- send email",
        "customerDestinationEmailAddress": "shimri.lotan@gmail.com",
        "toSendToCustomer": 0,
        "// comment toSendToCustomer": "0-no email, 1-draft email, 2- send email",
        "OCRPicFileExtention": "pdf",
        "// comment OCRfilesExtention": "will fetch the OCR picture file based on the given extention pdf of jpeg",
        "newProductsHeaders": ["מס פריט","שם פריט","ברקוד","מחיר קניה","ספק","מחיר מכירה","מחלקה","שורה מקורית","מזהה חשבונית","שם מחלקה"],
        "toNewProductMapping": [[1,8,1],[2,1,2],[3,2,2],[2,3,2],[7,4,1],[5,6,1],[8,10,1]],
        "// comment: last digit in mapping = Type : 1 - regulat, 2 - string ": "[column at items sheet,column at new product sheet, data type]",
        "newProductsItemsInducators": [10,7,9],
        "// comment newProductsItemsInducators": "[department name column,department number column, invoice identifier column]",
        "processPriceChange": [1,1,3],
        "// comment processPriceChnage [0] - costprice indicator (temp off), [1] - sales price indecator, [2] - threshold in percentage": "",
        "priceChangeHeader": ["שורה", "ברקוד", "מחיר חדש","שם פריט","מחלקה","שינוי עלות","מרווח נוכחי","מרווח מומלץ","מרווח תיאורטי","מחיר מכירה מקורי","עלות חדשה","מזהה חשבונית","שורה מקורית","שינוי מחיר"],
        "BOpackInvoiceListHeader": ["supplier", "date", "supplierCode", "invoiceNum", "invoiceSum", "remark"],
        "priceChangeMapping": [[2,2,2],[3,4,2],[8,5,1],[9,6,1],[1,13,1],[5,10,1],[7,11,1]],
        "// comment priceChangeMapping [from-column, to-column, data type]": "data types: 1 - regular, 2 - string",
        "priceChangeIndicators": [3,7,1.18,8,9,14,12,10,1.5,2,0.15],
        "// comment priceChangeIndicators": ["[saleNewPriceColumn, originalMarginColumn, VAT_multiplexer,recommendedMarginColumn,",
                                            "possibleMarginColumn,priceChangeIndicatorColumn,invoiceIdintifierColumn,OriginalSalePriceColumn,",
                                            "priceChangeThresholdPercentage,barcodeColumn,maxExtraMargin]"],
        "newProductsForBOheaders": ["מס פריט","שם פריט","ברקוד","מחיר קניה","ספק","מחיר מכירה","מחלקה","שורה מקורית","מזהה חשבונית","שם מחלקה"],
        "supplierColumnAtNewProductsForBOHeaders": 9,
        "BOtype": "all4shops",
        "// comment BOtype (back office type)": "can be comax or all4shops",
        "all4ShopsInvoiceHeadersArray": ["ID", "Code/Barcode", "Qty", "fldsaleprice"],
        "all4ShopsInvoiceMappingArray": [[1,1,1],[2,2,2],[4,3,1],[7,4,1]],
        "all4ShopsPriceChangeHeadersArray" : ["ID","Code/Barcode","Qty","fldsaleprice"],
        "all4ShopsPriceChangeMappingArray" : [[1,1,1],[2,2,2],[3,4,1]],
        "departmentsConfigFile":"C:/xampp/htdocs/website/configDir/Rimon_Departments.json",
        "BOEmailMessageTxtFile":"C:/xampp/htdocs/website/emailMessages/BO_result_email_message.txt",
        "supervisedProductsFile":"C:/xampp/htdocs/website/configDir/Supervised_products.json",
        "supplierParam": [{"supplierNDepartmentColumns":[5,0]},
                          {"Unilever": [9,33,0]},
                          {"Ridan": [83,33,0]},
                          {"Yafura": [112,33,0]},
                          {"Atias": [41,33,0]},
                          {"Sano": [60,33,0]},
                          {"BJ": [34,33,0]},
                          {"Neto": [33,33,0]},
                          {"AllMeat": [39,33,0]},
                          {"Dansell": [92,33,0]},
                          {"AbrahamSeeds": [999,33,0]},
                          {"Somech": [46,33,0]},
                          {"Yafura": [112,33,0]},
                          {"Globrands": [165,33,0]},
                          {"Dubek": [117,33,0]},
                          {"Caspin": [80,33,0]},
                          {"Soglowek": [50,33,1]},
                          {"StraussIcecream": [28,4,0]},
                          {"YLG": [5,33,0]},
                          {"Gad": [23,4,1]},
                          {"Tnuva": [20,4,0]},
                          {"StraussCool":[21,33,1]},
                          {"Mayan":[1099,33,1]},
                          {"Osem":[1,33,0]},
                          {"Berman":[43,33,0]},
                          {"StraussSweets":[10,33,0]},
                          {"StraussSnacks":[11,33,0]},
                          {"TnuvaMeat":[30,33,0]},
                          {"Sch":[140,33,0]},
                          {"LS":[103,33,0]},
                          {"Sagi":[1100,33,1]},
                          {"Diplomat":[38,33,1]},
                          {"Wisso":[51,33,0]},
                          {"CarmelWines":[557654,33,1]},
                          {"Sugat":[963258,33,1]},
                          {"Tara":[22,4,1]},
                          {"Shamay":[635241,33,0]},
                          {"Sides":[71,33,1]},
                          {"Tempo":[114,33,1]},
                          {"Willifood":[38,33,1]},
                          {"CentralCo":[110,33,1]},
                          {"AHtiv":[90,33,0]},
                          {"AFS":[454654,33,0]},
                          {"Etran":[47,33,0]},
                          {"BetterChoice":[111,33,0]},
                          {"Shipka":[26,33,0]},
                          {"Shufersal":[44,33,0]},
                          {"Dantes":[68,33,0]},
                          {"NASL":[515737,33,1]}],                               
        "// comment 1: supplierParam starcture": {"SupplierName": ["SupplierIndex","DepartmentIndex-not relevant","0-regular, 1-item price = LineTotal/Qty"]},
        "// comment 2: supplierParam ": "in 'supplierNDepartmentColumns':[X,Y] if X or Y = 0, the value will not be in new products sheet",
        "administratorName":"אלון"
      }
    ]
  }
  